labasic/.idea/.gitignore
labasic/.idea/inspectionProfiles/profiles_settings.xml
labasic/.idea/misc.xml
labasic/.idea/modules.xml
labasic/.idea/pythonProject.iml
labasic/.idea/workspace.xml
labasic/ai 6 lab.txt
labasic/ai-lab.txt
labasic/ann.py
labasic/astar.py
labasic/astarsim.py
labasic/gena.py
labasic/kmean.py
labasic/knn.py
labasic/linear.py
labasic/naive.py
labasic/pyproject.toml
labasic/q33333333333.txt
labasic/Setup.txt
labasic-0.1.1.dist-info/METADATA
labasic-0.1.1.dist-info/WHEEL
labasic-0.1.1.dist-info/RECORD
